loguru_extra/__init__.py
loguru_extra/loguru_extra.py
loguru_extra-0.1.7.dist-info/LICENSE
loguru_extra-0.1.7.dist-info/METADATA
loguru_extra-0.1.7.dist-info/WHEEL
loguru_extra-0.1.7.dist-info/RECORD
